odoo10_addon_project_gtd-10.0.1.0.0.99.dev10-py3.8-nspkg.pth
odoo/addons/project_gtd/README.rst
odoo/addons/project_gtd/__init__.py
odoo/addons/project_gtd/__manifest__.py
odoo/addons/project_gtd/project_gtd.py
odoo/addons/project_gtd/project_gtd_data.xml
odoo/addons/project_gtd/project_gtd_demo.xml
odoo/addons/project_gtd/project_gtd_view.xml
odoo/addons/project_gtd/i18n/ar.po
odoo/addons/project_gtd/i18n/bg.po
odoo/addons/project_gtd/i18n/bs.po
odoo/addons/project_gtd/i18n/ca.po
odoo/addons/project_gtd/i18n/cs.po
odoo/addons/project_gtd/i18n/da.po
odoo/addons/project_gtd/i18n/de.po
odoo/addons/project_gtd/i18n/el.po
odoo/addons/project_gtd/i18n/es.po
odoo/addons/project_gtd/i18n/es_AR.po
odoo/addons/project_gtd/i18n/es_CR.po
odoo/addons/project_gtd/i18n/es_EC.po
odoo/addons/project_gtd/i18n/es_MX.po
odoo/addons/project_gtd/i18n/es_VE.po
odoo/addons/project_gtd/i18n/et.po
odoo/addons/project_gtd/i18n/fi.po
odoo/addons/project_gtd/i18n/fr.po
odoo/addons/project_gtd/i18n/gl.po
odoo/addons/project_gtd/i18n/hr.po
odoo/addons/project_gtd/i18n/hu.po
odoo/addons/project_gtd/i18n/id.po
odoo/addons/project_gtd/i18n/it.po
odoo/addons/project_gtd/i18n/ja.po
odoo/addons/project_gtd/i18n/ko.po
odoo/addons/project_gtd/i18n/ko_KO.po
odoo/addons/project_gtd/i18n/lt.po
odoo/addons/project_gtd/i18n/lv.po
odoo/addons/project_gtd/i18n/mk.po
odoo/addons/project_gtd/i18n/mn.po
odoo/addons/project_gtd/i18n/nl.po
odoo/addons/project_gtd/i18n/nl_BE.po
odoo/addons/project_gtd/i18n/pl.po
odoo/addons/project_gtd/i18n/project_gtd.pot
odoo/addons/project_gtd/i18n/pt.po
odoo/addons/project_gtd/i18n/pt_BR.po
odoo/addons/project_gtd/i18n/pt_PT.po
odoo/addons/project_gtd/i18n/ro.po
odoo/addons/project_gtd/i18n/ru.po
odoo/addons/project_gtd/i18n/sl.po
odoo/addons/project_gtd/i18n/sq.po
odoo/addons/project_gtd/i18n/sv.po
odoo/addons/project_gtd/i18n/tlh.po
odoo/addons/project_gtd/i18n/tr.po
odoo/addons/project_gtd/i18n/uk.po
odoo/addons/project_gtd/i18n/vi.po
odoo/addons/project_gtd/i18n/zh_CN.po
odoo10_addon_project_gtd-10.0.1.0.0.99.dev10.dist-info/METADATA
odoo10_addon_project_gtd-10.0.1.0.0.99.dev10.dist-info/WHEEL
odoo10_addon_project_gtd-10.0.1.0.0.99.dev10.dist-info/namespace_packages.txt
odoo10_addon_project_gtd-10.0.1.0.0.99.dev10.dist-info/top_level.txt
odoo10_addon_project_gtd-10.0.1.0.0.99.dev10.dist-info/RECORD
